HowdenLLM/__init__.py
HowdenLLM/manager.py
howdenllmmanager-0.1.18.dist-info/METADATA
howdenllmmanager-0.1.18.dist-info/WHEEL
howdenllmmanager-0.1.18.dist-info/RECORD
